email_crawler/__init__.py
email_crawler/crawler.py
email_finder_website-0.4.dist-info/METADATA
email_finder_website-0.4.dist-info/WHEEL
email_finder_website-0.4.dist-info/entry_points.txt
email_finder_website-0.4.dist-info/top_level.txt
email_finder_website-0.4.dist-info/RECORD
