Metadata-Version: 2.1
Name: email-finder-website
Version: 0.4
Summary: A Python library to crawl websites and collect emails
Author: Sav Cal
Author-email: savadamcal@gmail.com
Classifier: Development Status :: 3 - Alpha
Classifier: Intended Audience :: Developers
Classifier: License :: OSI Approved :: MIT License
Classifier: Programming Language :: Python :: 3.8
Classifier: Programming Language :: Python :: 3.9
Classifier: Programming Language :: Python :: 3.10
Requires-Python: >=3.7
Requires-Dist: requests
Requires-Dist: lxml
